ma_finkg/__init__.py
ma_finkg/__main__.py
ma_finkg/config.py
ma_finkg/kg_construction_graph.py
ma_finkg/agents/__init__.py
ma_finkg/agents/data_processing_expert.py
ma_finkg/agents/domain_specific_expert.py
ma_finkg/agents/kg_expert.py
ma_finkg/agents/knowledge_extraction_expert.py
ma_finkg/agents/dspy/__init__.py
ma_finkg/agents/dspy/data_processing_expert.py
ma_finkg/agents/dspy/domain_specific_expert.py
ma_finkg/agents/dspy/kg_expert.py
ma_finkg/agents/dspy/knowledge_extraction_expert.py
ma_finkg/agents/dspy/optimizer.py
ma_finkg/models/__init__.py
ma_finkg/models/graph_state.py
ma_finkg/ontology/ontology_conllpp.json
ma_finkg/ontology/ontology_default.json
ma_finkg/ontology/ontology_fire.json
ma_finkg/ontology/ontology_nyt11.json
ma_finkg/ontology/ontology_refind.json
ma_finkg/ontology/ontology_scheme.json
ma_finkg/prompts/prompts_conllpp.yaml
ma_finkg/prompts/prompts_default.yaml
ma_finkg/prompts/prompts_fire.yaml
ma_finkg/prompts/prompts_nyt11.yaml
ma_finkg/prompts/prompts_refind.yaml
ma_finkg/utils/__init__.py
ma_finkg/utils/chunking.py
ma_finkg/utils/llm_factory.py
ma_finkg-0.1.7.dist-info/METADATA
ma_finkg-0.1.7.dist-info/WHEEL
ma_finkg-0.1.7.dist-info/entry_points.txt
ma_finkg-0.1.7.dist-info/top_level.txt
ma_finkg-0.1.7.dist-info/RECORD
